[
  {
    "id": 1,
    "data": [
      {
        "scene": "用户在设置中启用应用密码锁时，应用要求输入并再次确认四位密码，将结果返回设置页后分位写入本地偏好。",
        "purpose": "设置应用解锁密码",
        "source": "用户在密码锁页面输入",
        "item": "四位应用解锁密码和验证结果",
        "frequency": "仅在用户设置或修改密码锁时",
        "processing": "本地校验两次输入并写入应用偏好",
        "storage": "以四个偏好字段保存在设备本地；所选代码未显示额外加密",
        "recipient": "本应用",
        "thirdparty": "不通过该代码路径上传或共享给第三方",
        "switchpath": "可在设置中验证现有密码后关闭密码锁；忘记密码可能影响应用访问"
      }
    ],
    "permissions": []
  }
]
