[
  {
    "id": "FLOW_BIOMETRIC_APP_LOCK",
    "data": [
      {
        "scene": "Biometric Authentication Result (Fingerprint/Face)",
        "purpose": "When the user enables app lock, the app calls Android BiometricPrompt API to verify identity via system-level fingerprint or face recognition. Access is granted only on successful verification. The app only receives the success/failure result and never accesses raw biometric data.",
        "source": "Home Assistant Companion",
        "item": "Biometric Authentication Result (Fingerprint/Face)",
        "frequency": "Periodic",
        "processing": "Uploaded to server",
        "storage": "Server-side storage",
        "recipient": "Home Assistant server (user self-hosted)",
        "thirdparty": "No third-party data sharing",
        "switchpath": "Settings -> Sensor Management"
      }
    ],
    "permissions": []
  }
]